dh5mbp/__init__.py
dh5mbp/static/css/dh5mbp/jquery.mobile-1.3.1.min.css
dh5mbp/static/css/dh5mbp/jquery.mobile-1.3.2.min.css
dh5mbp/static/css/dh5mbp/jquery.mobile-1.4.0.min.css
dh5mbp/static/css/dh5mbp/jquery.mobile-1.4.1.min.css
dh5mbp/static/css/dh5mbp/jquery.mobile-1.4.2.min.css
dh5mbp/static/js/dh5mbp/jquery-addToHome.min.js
dh5mbp/static/js/dh5mbp/jquery.mobile-1.3.1.min.js
dh5mbp/static/js/dh5mbp/jquery.mobile-1.3.2.min.js
dh5mbp/static/js/dh5mbp/jquery.mobile-1.4.0.min.js
dh5mbp/static/js/dh5mbp/jquery.mobile-1.4.1.min.js
dh5mbp/static/js/dh5mbp/jquery.mobile-1.4.2.min.js
dh5mbp/templates/dh5mbp/base.html
django_html5_mobile_boilerplate-1.0.5.dist-info/DESCRIPTION.rst
django_html5_mobile_boilerplate-1.0.5.dist-info/METADATA
django_html5_mobile_boilerplate-1.0.5.dist-info/pydist.json
django_html5_mobile_boilerplate-1.0.5.dist-info/RECORD
django_html5_mobile_boilerplate-1.0.5.dist-info/top_level.txt
django_html5_mobile_boilerplate-1.0.5.dist-info/WHEEL
