Metadata-Version: 2.0
Name: django-html5-mobile-boilerplate
Version: 1.0.5
Summary: A framework that includes the Django HTML5 boilerplate template into your django project and augments it with mobile support.
Home-page: https://github.com/mattsnider/django-html5-boilerplate
Author: Matt Snider
Author-email: admin@mattsnider.com
License: MIT
Keywords: python,django,html5,boilerplate,mobile,ios,jquery
Platform: any
Classifier: Programming Language :: Python
Classifier: License :: OSI Approved :: MIT License
Classifier: Operating System :: OS Independent
Classifier: Development Status :: 3 - Alpha
Classifier: Environment :: Web Environment
Classifier: Intended Audience :: Developers
Classifier: Topic :: Software Development :: Libraries :: Python Modules
Requires-Dist: django (>=1.3)
Requires-Dist: django-html5-boilerplate (>=1.0.5)
